{
  "slides": [
    {
      "name": "welcome",
      "basicReplacements": {
        "name": "Becky Hwang"
      }
    },
    {
      "name": "practice-summary",
      "basicReplacements": {
        "practice-count": 29,
        "practice-percentage": "90.63%",
        "total-yardage": "74200"
      },
      "visible": [
        "total-yardage"
      ]
    },
    {
      "name": "swims-summary",
      "basicReplacements": {
        "individual-swim-count": 10,
        "relay-swim-count": 10,
        "total-points": "44"
      },
      "templateReplacements": [
        {
          "name": "states-qualified-event",
          "sets": [
            {
              "event": "200 IM"
            },
            {
              "event": "50 Freestyle"
            },
            {
              "event": "100 Freestyle"
            },
            {
              "event": "100 Backstroke"
            },
            {
              "event": "100 Breaststroke"
            }
          ]
        }
      ],
      "visible": [
        "scored-points",
        "states-qualified-events"
      ]
    },
    {
      "name": "goodbye"
    }
  ]
}